Workbook

Sheet Cover
A2: ACCOUNT RECONCILIATION WORKBOOK
A6: Record to Report — GL & Bank Reconciliation | FY 2025-26
B10: Company: | C10: XYZ Manufacturing Pvt. Ltd.
B11: Prepared By: | C11: Accounts Team — R2R Division
B12: Review Period: | C12: March 2026 (FY 2025-26)
B13: As On Date: | C13: 31-Mar-2026
B14: Approved By: | C14: Finance Controller
B18: WORKBOOK INDEX
B19: # | C19: Sheet Name | D19: Description | G19: Status
B20: 1 | C20: GL Data | D20: General Ledger transactions for March 2026 | G20: ✔ Complete
B21: 2 | C21: Bank Statement | D21: Bank statement entries for March 2026 | G21: ✔ Complete
B22: 3 | C22: Bank Recon | D22: Bank vs GL matching & reconciliation statement | G22: ✔ Complete
B23: 4 | C23: Subledger Recon | D23: AR/AP Subledger vs GL control account reconciliation | G23: ✔ Complete
B24: 5 | C24: Recon Summary | D24: Executive summary of all reconciliation results | G24: ✔ Complete

Sheet GL Data
A1: GENERAL LEDGER — TRANSACTION DATA | March 2026
A2: Account: 1001 — Current Account (HDFC Bank) | Currency: INR
A3: Txn No. | B3: Date | C3: Description | D3: Voucher Type | E3: Debit (₹) | F3: Credit (₹) | G3: Running Balance (₹) | H3: Reference | I3: Posted By
A4: GL-0001 | B4: 01-Mar-26 | C4: Opening Balance b/f | D4: Opening | E4: 3250000 | G4: 3250000 | I4: OB-2026
A5: GL-0002 | B5: 02-Mar-26 | C5: Customer Payment — Reliance Retail | D5: Receipt | E5: 185000 | G5: =G4+IF(E5="",0,E5)-IF(F5="",0,F5) -> 3435000 | H5: INV-2201 | I5: Priya S.
A6: GL-0003 | B6: 03-Mar-26 | C6: Vendor Payment — Tata Steel | D6: Payment | F6: 95000 | G6: =G5+IF(E6="",0,E6)-IF(F6="",0,F6) -> 3340000 | H6: PO-4501 | I6: Rohan M.
A7: GL-0004 | B7: 05-Mar-26 | C7: Salary Disbursement — March | D7: Payment | F7: 420000 | G7: =G6+IF(E7="",0,E7)-IF(F7="",0,F7) -> 2920000 | H7: SAL-0326 | I7: Rohan M.
A8: GL-0005 | B8: 07-Mar-26 | C8: Customer Payment — ITC Ltd | D8: Receipt | E8: 210000 | G8: =G7+IF(E8="",0,E8)-IF(F8="",0,F8) -> 3130000 | H8: INV-2202 | I8: Priya S.
A9: GL-0006 | B9: 08-Mar-26 | C9: Office Rent — March | D9: Payment | F9: 75000 | G9: =G8+IF(E9="",0,E9)-IF(F9="",0,F9) -> 3055000 | H9: RENT-326 | I9: Anita K.
A10: GL-0007 | B10: 10-Mar-26 | C10: Customer Payment — Nestle India | D10: Receipt | E10: 155000 | G10: =G9+IF(E10="",0,E10)-IF(F10="",0,F10) -> 3210000 | H10: INV-2203 | I10: Priya S.
A11: GL-0008 | B11: 12-Mar-26 | C11: Bank Charges | D11: Misc | F11: 1200 | G11: =G10+IF(E11="",0,E11)-IF(F11="",0,F11) -> 3208800 | H11: BC-0326 | I11: System
A12: GL-0009 | B12: 14-Mar-26 | C12: Vendor Payment — Godrej Consumer | D12: Payment | F12: 68000 | G12: =G11+IF(E12="",0,E12)-IF(F12="",0,F12) -> 3140800 | H12: PO-4502 | I12: Rohan M.
A13: GL-0010 | B13: 15-Mar-26 | C13: Customer Payment — Dabur India | D13: Receipt | E13: 97000 | G13: =G12+IF(E13="",0,E13)-IF(F13="",0,F13) -> 3237800 | H13: INV-2204 | I13: Priya S.
A14: GL-0011 | B14: 17-Mar-26 | C14: Advance to Supplier — ABC Traders | D14: Payment | F14: 50000 | G14: =G13+IF(E14="",0,E14)-IF(F14="",0,F14) -> 3187800 | H14: ADV-101 | I14: Anita K.
A15: GL-0012 | B15: 18-Mar-26 | C15: Interest Income | D15: Receipt | E15: 8500 | G15: =G14+IF(E15="",0,E15)-IF(F15="",0,F15) -> 3196300 | H15: INT-0326 | I15: System
A16: GL-0013 | B16: 20-Mar-26 | C16: Customer Payment — Marico Ltd | D16: Receipt | E16: 130000 | G16: =G15+IF(E16="",0,E16)-IF(F16="",0,F16) -> 3326300 | H16: INV-2205 | I16: Priya S.
A17: GL-0014 | B17: 22-Mar-26 | C17: Utilities — Electricity Bill | D17: Payment | F17: 32000 | G17: =G16+IF(E17="",0,E17)-IF(F17="",0,F17) -> 3294300 | H17: UTIL-326 | I17: Rohan M.
A18: GL-0015 | B18: 24-Mar-26 | C18: Customer Payment — P&G India | D18: Receipt | E18: 175000 | G18: =G17+IF(E18="",0,E18)-IF(F18="",0,F18) -> 3469300 | H18: INV-2206 | I18: Priya S.
A19: GL-0016 | B19: 25-Mar-26 | C19: TDS Payment to Govt | D19: Payment | F19: 45000 | G19: =G18+IF(E19="",0,E19)-IF(F19="",0,F19) -> 3424300 | H19: TDS-326 | I19: Anita K.
A20: GL-0017 | B20: 27-Mar-26 | C20: Vendor Payment — Hindustan Unilever | D20: Payment | F20: 88000 | G20: =G19+IF(E20="",0,E20)-IF(F20="",0,F20) -> 3336300 | H20: PO-4503 | I20: Rohan M.
A21: GL-0018 | B21: 28-Mar-26 | C21: Customer Payment — Britannia | D21: Receipt | E21: 89000 | G21: =G20+IF(E21="",0,E21)-IF(F21="",0,F21) -> 3425300 | H21: INV-2207 | I21: Priya S.
A22: GL-0019 | B22: 29-Mar-26 | C22: Miscellaneous Expense | D22: Payment | F22: 15000 | G22: =G21+IF(E22="",0,E22)-IF(F22="",0,F22) -> 3410300 | H22: MISC-326 | I22: Anita K.
A23: GL-0020 | B23: 31-Mar-26 | C23: Bank Charges — NEFT | D23: Misc | F23: 500 | G23: =G22+IF(E23="",0,E23)-IF(F23="",0,F23) -> 3409800 | H23: BC-0327 | I23: System
C24: TOTAL MOVEMENTS | E24: =SUM(E4:E23) -> 4299500 | F24: =SUM(F4:F23) -> 889700
A26: Closing Balance as per GL (31-Mar-2026) → | G26: =G23 -> 3409800

Sheet Bank Statement
A1: BANK STATEMENT — HDFC BANK | A/C: XXXX-XXXX-7842 | March 2026
A2: IFSC: HDFC0001234 | Branch: Connaught Place, New Delhi | Statement Period: 01-Mar-2026 to 31-Mar-2026
A3: Value Date | B3: Description | C3: Cheque/Ref No. | D3: Debit (₹) | E3: Credit (₹) | F3: Balance (₹) | G3: Match Status | H3: GL Ref
A4: 02-Mar-26 | B4: NEFT Cr - Reliance Retail | C4: NEFT2201 | E4: 185000 | F4: 3435000 | G4: Matched | H4: INV-2201
A5: 03-Mar-26 | B5: RTGS Dr - Tata Steel | C5: RTGS4501 | D5: 95000 | F5: 3340000 | G5: Matched | H5: PO-4501
A6: 05-Mar-26 | B6: Salary - March 2026 | C6: SAL0326 | D6: 420000 | F6: 2920000 | G6: Matched | H6: SAL-0326
A7: 06-Mar-26 | B7: NEFT Cr - ITC Ltd | C7: NEFT2202 | E7: 210000 | F7: 3130000 | G7: Matched | H7: INV-2202
A8: 08-Mar-26 | B8: Office Rent - Mar | C8: RENT326 | D8: 75000 | F8: 3055000 | G8: Matched | H8: RENT-326
A9: 10-Mar-26 | B9: NEFT Cr - Nestle India | C9: NEFT2203 | E9: 155000 | F9: 3210000 | G9: Matched | H9: INV-2203
A10: 12-Mar-26 | B10: Bank Charges - Mar | C10: CHGS326 | D10: 1200 | F10: 3208800 | G10: Matched | H10: BC-0326
A11: 14-Mar-26 | B11: RTGS Dr - Godrej Consumer | C11: RTGS4502 | D11: 68000 | F11: 3140800 | G11: Matched | H11: PO-4502
A12: 15-Mar-26 | B12: NEFT Cr - Dabur India | C12: NEFT2204 | E12: 97000 | F12: 3237800 | G12: Matched | H12: INV-2204
A13: 16-Mar-26 | B13: DD Dr - ABC Traders | C13: DD101 | D13: 50000 | F13: 3187800 | G13: Matched | H13: ADV-101
A14: 18-Mar-26 | B14: Interest Credit | C14: INT326 | E14: 8500 | F14: 3196300 | G14: Matched | H14: INT-0326
A15: 19-Mar-26 | B15: NEFT Cr - Marico Ltd | C15: NEFT2205 | E15: 130000 | F15: 3326300 | G15: Matched | H15: INV-2205
A16: 22-Mar-26 | B16: Electricity Bill | C16: UTIL326 | D16: 32000 | F16: 3294300 | G16: Matched | H16: UTIL-326
A17: 24-Mar-26 | B17: NEFT Cr - P&G India | C17: NEFT2206 | E17: 175000 | F17: 3469300 | G17: Matched | H17: INV-2206
A18: 25-Mar-26 | B18: TDS Payment | C18: TDS326 | D18: 45000 | F18: 3424300 | G18: Matched | H18: TDS-326
A19: 26-Mar-26 | B19: RTGS Dr - Hindustan Unilever | C19: RTGS4503 | D19: 88000 | F19: 3336300 | G19: Matched | H19: PO-4503
A20: 28-Mar-26 | B20: NEFT Cr - Britannia | C20: NEFT2207 | E20: 89000 | F20: 3425300 | G20: Matched | H20: INV-2207
A21: 29-Mar-26 | B21: Miscellaneous Exp | C21: MISC326 | D21: 15000 | F21: 3410300 | G21: Matched | H21: MISC-326
A22: 30-Mar-26 | B22: Direct Debit - Insurance Premium | C22: DD-INS01 | D22: 22000 | F22: 3388300 | G22: Unmatched
A23: 31-Mar-26 | B23: NEFT Cr - Varun Beverages (late credit) | C23: NEFT2208 | E23: 45000 | F23: 3433300 | G23: Unmatched
A24: 31-Mar-26 | B24: Bank Charges - NEFT | C24: CHGS327 | D24: 500 | F24: 3432800 | G24: Matched | H24: BC-0327
A25: Closing Balance as per Bank Statement (31-Mar-2026) → | F25: 3432800

Sheet Bank Recon
A1: BANK RECONCILIATION STATEMENT | 31st March 2026
A3: PART A — BALANCE AS PER GENERAL LEDGER
B4: Particulars | E4: Amount (₹)
B5: Closing Balance as per GL (31-Mar-2026) | E5: ='GL Data'!G26 -> 3409800
B6: Add: Bank Credit not recorded in GL
B7: — NEFT from Varun Beverages (late entry) | E7: 45000 | F7: Unmatched in Bank
B8: Less: Bank Debit not recorded in GL
B9: — Insurance Premium DD (not booked) | E9: -22000 | F9: Unmatched in Bank
B10: — Bank Charges NEFT (already recorded) | E10: 0 | F10: Already matched
B11: Adjusted Balance as per GL | E11: =E5+E7+E8 -> 3454800
A13: PART B — BALANCE AS PER BANK STATEMENT
B14: Particulars | E14: Amount (₹)
B15: Closing Balance as per Bank Statement (31-Mar-2026) | E15: 3432800
B16: Less: Deposits in Transit (not yet credited by bank)
B17: — No outstanding deposits in transit | E17: 0
B18: Add: Outstanding Cheques (issued not yet presented)
B19: — No outstanding cheques | E19: 0
B20: Adjusted Balance as per Bank | E20: 3432800
A22: RECONCILIATION CHECK
B23: Difference (GL Adjusted − Bank Adjusted) | E23: =E11-E20 -> 22000
B24: Reconciliation Status | E24: =IF(E23=0,"✔ RECONCILED","✘ DIFFERENCE EXISTS") -> ✘ DIFFERENCE EXISTS
A26: UNMATCHED / RECONCILING ITEMS
A27: # | B27: Description | D27: Date | E27: Amount (₹) | F27: Action Required
A28: 1 | B28: Insurance Premium DD | D28: Bank Only | E28: 22000 | F28: Book journal entry: Dr Prepaid Insurance / Cr Bank
A29: 2 | B29: NEFT from Varun Beverages | D29: Bank Only | E29: 45000 | F29: Post receipt entry in GL against INV-pending

Sheet Subledger Recon
A1: SUBLEDGER vs GL CONTROL ACCOUNT RECONCILIATION | 31st March 2026
A3: SECTION 1 — ACCOUNTS RECEIVABLE (AR) RECONCILIATION
A4: Customer | B4: Subledger Balance (₹) | C4: GL Control A/c (₹) | D4: Difference (₹) | E4: Status | F4: Aging | G4: Last Payment | H4: Remarks
A5: Reliance Retail | B5: 0 | C5: 0 | D5: 0 | E5: ✔ Matched | F5: Current | G5: 31-Mar-26
A6: Tata Consumer | B6: 88000 | C6: 88000 | D6: 0 | E6: ✔ Matched | F6: 31-60 Days | G6: Feb-26
A7: ITC Ltd | B7: 174000 | C7: 174000 | D7: 0 | E7: ✔ Matched | F7: 31-60 Days | G7: Feb-26
A8: Britannia Inds | B8: 89000 | C8: 89000 | D8: 0 | E8: ✔ Matched | F8: 31-60 Days | G8: Feb-26
A9: Dabur India | B9: 37000 | C9: 37000 | D9: 0 | E9: ✔ Matched | F9: 31-60 Days | G9: Feb-26
A10: P&G India | B10: 112000 | C10: 112000 | D10: 0 | E10: ✔ Matched | F10: 31-60 Days | G10: Feb-26
A11: Marico Ltd | B11: 86000 | C11: 86000 | D11: 0 | E11: ✔ Matched | F11: 31-60 Days | G11: Feb-26
A12: Nestle India | B12: 0 | C12: 0 | D12: 0 | E12: ✔ Matched | F12: Current | G12: 31-Mar-26
A13: Varun Beverages | B13: 100000 | C13: 55000 | D13: 45000 | E13: ✘ Variance | F13: 31-60 Days | G13: Feb-26 | H13: Late bank credit not updated in GL
A14: Hindustan Foods | B14: 125500 | C14: 125500 | D14: 0 | E14: ✔ Matched | F14: 31-60 Days | G14: Feb-26
A15: Emami Ltd | B15: 85000 | C15: 85000 | D15: 0 | E15: ✔ Matched | F15: 31-60 Days | G15: Feb-26
A16: Godrej Consumer | B16: 31000 | C16: 31000 | D16: 0 | E16: ✔ Matched | F16: 31-60 Days | G16: Feb-26
A17: Colgate Palmolive | B17: 0 | C17: 0 | D17: 0 | E17: ✔ Matched | F17: Current | G17: 31-Mar-26
A18: TOTAL | B18: 927500 | C18: 882500 | D18: 45000
A20: SECTION 2 — ACCOUNTS PAYABLE (AP) RECONCILIATION
A21: Vendor | B21: Subledger Balance (₹) | C21: GL Control A/c (₹) | D21: Difference (₹) | E21: Status | F21: Due Date | G21: Invoice Ref | H21: Remarks
A22: Tata Steel | B22: 95000 | C22: 95000 | D22: 0 | E22: ✔ Matched | F22: 15-Apr-26 | G22: PO-4501
A23: Godrej Consumer | B23: 68000 | C23: 68000 | D23: 0 | E23: ✔ Matched | F23: 31-60 Days | G23: PO-4502
A24: Hindustan Unilever | B24: 88000 | C24: 88000 | D24: 0 | E24: ✔ Matched | F24: 10-Apr-26 | G24: PO-4503
A25: ABC Traders | B25: 50000 | C25: 50000 | D25: 0 | E25: ✔ Matched | F25: Advance — Pending | G25: ADV-101
A26: Reliance Industries | B26: 120000 | C26: 120000 | D26: 0 | E26: ✔ Matched | F26: 05-Apr-26 | G26: PO-4504
A27: Asian Paints | B27: 45000 | C27: 45000 | D27: 0 | E27: ✔ Matched | F27: 25-Apr-26 | G27: PO-4505
A28: Bajaj Electricals | B28: 33000 | C28: 33000 | D28: 0 | E28: ✔ Matched | F28: 30-Apr-26 | G28: PO-4506
A29: Havells India | B29: 72000 | C29: 72000 | D29: 0 | E29: ✔ Matched | F29: 12-Apr-26 | G29: PO-4507
A30: Pidilite | B30: 28000 | C30: 28000 | D30: 0 | E30: ✔ Matched | F30: 18-Apr-26 | G30: PO-4508
A31: UPL Ltd | B31: 65000 | C31: 75000 | D31: -10000 | E31: ✘ Variance | F31: 22-Apr-26 | G31: PO-4509 | H31: GL shows ₹75,000; Subledger shows ₹65,000 — ₹10,000 excess in GL; pending vendor invoice confirmation to update subledger
A32: TOTAL | B32: 664000 | C32: 674000 | D32: -10000

Sheet Recon Summary
A1: RECONCILIATION SUMMARY DASHBOARD | March 2026 | XYZ Manufacturing Pvt. Ltd.
A3: KEY RECONCILIATION METRICS
A4: GL Closing Balance | C4: Bank Closing Balance | E4: Bank Recon Difference
A5: ='Bank Recon'!E5 -> 3409800 | C5: ='Bank Recon'!E18 -> 0 | E5: =C5-A5 -> -3409800
A7: AR Subledger Balance | C7: AR GL Control Balance | E7: AR Variance
A8: ₹9,27,500 | C8: ₹8,82,500 | E8: ₹45,000
A10: AP Subledger Balance | C10: AP GL Control Balance | E10: AP Variance
A11: ₹6,64,000 | C11: ₹6,74,000 | E11: ₹10,000
A18: RECONCILIATION STATUS SUMMARY
A19: # | B19: Reconciliation Type | C19: GL Balance (₹) | D19: Sub/Bank Balance (₹) | E19: Variance (₹) | F19: Status | G19: Action Required
A20: 1 | B20: Bank Reconciliation (GL vs Bank) | C20: ='Bank Recon'!E5 -> 3409800 | D20: ='Bank Recon'!E18 -> 0 | E20: =D20-C20 -> -3409800 | F20: ⚠ Minor Variance | G20: Book 2 unmatched items — see Bank Recon sheet
A21: 2 | B21: AR Subledger vs GL Control A/c | C21: 882500 | D21: 927500 | E21: 45000 | F21: ✘ Variance | G21: Update GL for Varun Beverages late credit
A22: 3 | B22: AP Subledger vs GL Control A/c | C22: 674000 | D22: 664000 | E22: -10000 | F22: ✘ Variance | G22: Verify UPL Ltd invoice & update subledger
A23: 4 | B23: Intercompany Reconciliation | C23: 0 | D23: 0 | E23: 0 | F23: ✔ Reconciled | G23: No intercompany transactions this period
A24: 5 | B24: Prepaid & Accruals Recon | C24: 125000 | D24: 125000 | E24: 0 | F24: ✔ Reconciled | G24: All schedules match
A26: SIGN-OFF & APPROVALS
A27: Role | B27: Name | C27: Signature | D27: Date | E27: Comments
A28: Prepared By | B28: Accounts Associate — R2R | C28: ____________ | D28: 31-Mar-26
A29: Reviewed By | B29: R2R Team Lead | C29: ____________ | D29: 31-Mar-26
A30: Approved By | B30: Finance Controller | C30: ____________ | D30: 31-Mar-26
